simpleufcs.py
simpleufcs-1.0.0.dist-info/LICENSE
simpleufcs-1.0.0.dist-info/METADATA
simpleufcs-1.0.0.dist-info/WHEEL
simpleufcs-1.0.0.dist-info/top_level.txt
simpleufcs-1.0.0.dist-info/RECORD
